MANIFEST.in
README.md
requirements.txt
setup.cfg
setup.py
timex/__init__.py
timex/expression.py
timex/lexer.py
timex/parser.py
timex.egg-info/PKG-INFO
timex.egg-info/SOURCES.txt
timex.egg-info/dependency_links.txt
timex.egg-info/not-zip-safe
timex.egg-info/pbr.json
timex.egg-info/requires.txt
timex.egg-info/top_level.txt