Metadata-Version: 1.1
Name: timex
Version: 0.20.0
Summary: A time expressions library implementing a mini-language for manipulating datetimes
Home-page: https://github.com/stackforge/stacktach-timex
Author: Monsyne Dragon
Author-email: mdragon@rackspace.com
License: Apache License (2.0)
Keywords: datetime manipulation transformation DSL
Platform: UNKNOWN
Classifier: Development Status :: 3 - Alpha
Classifier: License :: OSI Approved :: Apache Software License
Classifier: Operating System :: POSIX :: Linux
Classifier: Programming Language :: Python :: 2.6
Classifier: Programming Language :: Python :: 2.7
